pytest_track/__init__.py
pytest_track/confluence.py
pytest_track/html_coverage.py
pytest_track/models.py
pytest_track/plugin.py
pytest_track/templates/__init__.py
pytest_track/templates/html_coverage.html
pytest_track-0.1.3.dist-info/LICENSE
pytest_track-0.1.3.dist-info/METADATA
pytest_track-0.1.3.dist-info/WHEEL
pytest_track-0.1.3.dist-info/entry_points.txt
pytest_track-0.1.3.dist-info/top_level.txt
pytest_track-0.1.3.dist-info/RECORD
